yamllint_junit_bootstrap/__init__.py
yamllint_junit_bootstrap/__main__.py
yamllint_junit_bootstrap/bootstrap.py
yamllint_junit-0.10.1.dist-info/LICENSE.txt
yamllint_junit-0.10.1.dist-info/METADATA
yamllint_junit-0.10.1.dist-info/WHEEL
yamllint_junit-0.10.1.dist-info/entry_points.txt
yamllint_junit-0.10.1.dist-info/top_level.txt
yamllint_junit-0.10.1.dist-info/RECORD
