Metadata-Version: 2.1
Name: yamllint-junit
Version: 0.10.1
Summary: yamllint to JUnit converter.
Home-page: https://github.com/wasilak/yamllint-junit
Download-URL: https://github.com/wasilak/yamllint-junit/archive/0.10.1.tar.gz
Author: wasil
Author-email: piotr.m.boruc@gmail.com
Keywords: yaml,junit
License-File: LICENSE.txt
Requires-Dist: yamllint
